solshade/__init__.py
solshade/cli.py
solshade/irradiance.py
solshade/solar.py
solshade/terrain.py
solshade/utils.py
solshade/viz.py
solshade-0.1.0.dist-info/METADATA
solshade-0.1.0.dist-info/WHEEL
solshade-0.1.0.dist-info/entry_points.txt
solshade-0.1.0.dist-info/licenses/LICENSE
solshade-0.1.0.dist-info/RECORD
