Metadata-Version: 2.4
Name: solshade
Version: 0.1.0
Summary: Terrain-aware solar illumination modeling using DEMs and orbital sun geometry.
Project-URL: Documentation, https://solshade.readthedocs.io
Project-URL: Source, https://github.com/amanchokshi/solshade
Project-URL: Homepage, https://github.com/amanchokshi/solshade
Project-URL: Issues, https://github.com/amanchokshi/solshade/issues
Author-email: Aman Chokshi <aman.chokshi@mcgill.ca>
License: MIT
License-File: LICENSE
Keywords: DEM,GIS,geospatial,illumination,solar,terrain
Classifier: License :: OSI Approved :: MIT License
Classifier: Operating System :: OS Independent
Classifier: Programming Language :: Python :: 3
Requires-Python: >=3.13
Requires-Dist: cmasher>=1.9.2
Requires-Dist: joblib>=1.5.1
Requires-Dist: matplotlib>=3.10.5
Requires-Dist: more-itertools>=10.7.0
Requires-Dist: numba==0.61.2
Requires-Dist: numpy==2.2
Requires-Dist: pandas>=2.3.1
Requires-Dist: rasterio>=1.4.3
Requires-Dist: rich>=14.1.0
Requires-Dist: rioxarray>=0.19.0
Requires-Dist: scipy>=1.16.1
Requires-Dist: skyfield>=1.53
Requires-Dist: typer>=0.16.0
